imageprocessing/__init__.py
imageprocessing/ImageProcessing.py
imageprocessing-0.1.1.dist-info/WHEEL
imageprocessing-0.1.1.dist-info/METADATA
imageprocessing-0.1.1.dist-info/RECORD
