Metadata-Version: 2.1
Name: imageprocessing
Version: 0.1.1
Summary: This is a package that will allow you to remove the background of any image and replace it with another
Author: Raviish Panicker
Author-email: panicker.raviish2@gmail.com
Requires-Python: >=3.8,<4.0
Classifier: Programming Language :: Python :: 3
Classifier: Programming Language :: Python :: 3.8
